labos/__init__.py
labos/ajuste.py
labos/ejemplo_instrumentos.py
labos/notificacion_bot.py
labos/propagacion.py
labos/señales.py
labos-0.1.2.7.dist-info/METADATA
labos-0.1.2.7.dist-info/WHEEL
labos-0.1.2.7.dist-info/RECORD
