Metadata-Version: 2.1
Name: labos
Version: 0.1.2.7
Summary: Paquete para trabajar en el labo
Author: joctavio287
Author-email: joctavio287@gmail.com
Requires-Python: >=3.8,<3.12
Classifier: Programming Language :: Python :: 3
Classifier: Programming Language :: Python :: 3.8
Classifier: Programming Language :: Python :: 3.9
Classifier: Programming Language :: Python :: 3.10
Classifier: Programming Language :: Python :: 3.11
Requires-Dist: matplotlib (>=3.2.2)
Requires-Dist: numpy (>=1.21)
Requires-Dist: requests (>=2.2)
Requires-Dist: scipy (>=1.10.0)
Requires-Dist: sympy (>=1.10)
